<scrape><title>The dinner</title><review_date>Nov 15, 2014</review_date><review_language></review_language><review_id>1107010247</review_id><author>Alecx</author><rating>did not like it</rating><text>I waited a few days after reading the book to see if i would change my mind about it. Nope. Really disliked this book. The narrator was quite unreliable so I was never sure of the things he talked about actually happened. None of the characters were likable and I just couldn't quite follow their thought process.</text></scrape>