<scrape><title>The dinner</title><review_date>Dec 25, 2016</review_date><review_language>nl</review_language><review_id>1832947954</review_id><author>Bodine</author><rating>liked it</rating><text>Het leest als een trein, het hoofdpersonage is interessant, het tijdspanne waarin het speelt ook en bovendien de toon: alles is een beetje als het werkstuk, kan eigenlijk net niet maar is juist daarom fijn om te lezen. De stijl is ook prettig.
3 sterren, niet omdat het een slecht boek is (het was juist heel fijn om te lezen), maar meer omdat ik het gevoel heb dat dit het soort boek is waarover ik over een jaar niets meer weet.</text></scrape>