<scrape><title>The dinner</title><review_date>Jan 02, 2017</review_date><review_language>nl</review_language><review_id>1861080792</review_id><author>Annika</author><rating>really liked it</rating><text>Bedachtzaam. Er zijn genoeg stukken in het boek die voor mij verre van interessant waren en ik me afvroeg waarom dit bij het verhaal wordt weergeven (het verslag van Michel over de doodstraf bijv.). Sommige delen waren gewoon ronduit extreem lang en uitgebreid. Ik stuitte op iets wat niet klopte (Serge’s tournedos die eerst in drie happen werd opgegeten, toen vier, en toen weer drie.).Toch vond ik verhaal nadenkend, waarom zou je zo iets voor je familie over hebben? De manier waarop het probleem bekend werd gemaakt ben ik eigenlijk best wel een fan van, het volgen van een vijf-gangenmenu, op volgorde van belangrijkheid. </text></scrape>