<scrape><title>The dinner</title><review_date>Jun 21, 2017</review_date><review_language></review_language><review_id>2035368228</review_id><author>Jenna</author><rating>really liked it</rating><text>This novel was actually really good but it's really ambiguous. There are events that take place that are never really elaborated on. I like how the author wrote the characters and the more you got to know their story the more your views changed about them. Full review: https://abibliophobe1989.wordpress.co...</text></scrape>