<scrape><title>The dinner</title><review_date>Oct 09, 2018</review_date><review_language>id</review_language><review_id>2557496492</review_id><author>Aya</author><rating>liked it</rating><text>100 halaman pertama, ga ada kejadian berarti, ga ada konflik apapun yang muncul. Tapi setelahnya pertanyaan mulai muncul akibat kejanggalan dan kejadian di hidup si tokoh utama ini. Narasinya pakai sudut pandang orang pertama, yang bisa dibilang ... aneh (setelah baca review dari beberapa orang, ternyata si tokoh utama ini punya kelainan/penyakit mental).Selain itu, gue kurang nyaman dengan perpindahan setting waktu di novel ini. Jelas sih perpindahannya, tapi kurang nyaman bagi gue. Selain itu, si tokoh utama ini terlalu banyak mikirin hal-hal yang menurut gue remeh.Misterinya bikin gue pengen terus baca. Ada sesuatu dari narasi cerita yang meskipun ga nyaman, tapi ketika gue taro buku ini untuk istirahat sebentar, ada perasaan penasaran, kenapa dan apa yang akan terjadi selanjutnya? Akan dibawa kemana cerita ini? Apakah pembaca akan langsung dikasih jawaban atau diputer-puter dulu (hampir tiga perempat buku ini memang muter-muter ceritanya).Ketika konfliknya mulai menanjak dan gue udah berpikir macem-macem tentang klimaksnya, ternyata ... ga terlalu mencengangkan. Tapi (lagi-lagi setelah baca penjelasan di review beberapa orang) ternyata di balik tindakan yang dilakukan keluarga ini, ada penyakit mental yang mendasarinya. Jadi kalau dipikir-pikir lagi, cerita ini memang tentang orang-orang 'sakit'.</text></scrape>