<scrape><title>The dinner</title><review_date>Dec 20, 2019</review_date><review_language>bg</review_language><review_id>3084405831</review_id><author>Slav Ivanov</author><rating>it was amazing</rating><text>Завладяваща книга, която ме държеше в очакване до края. От доста време не съм бил така нетърпелив да се върна към книга. Поставя интересния въпрос за това доколко родителите предизвикват действията на децата си, при положение че носят същите гени и са възпитани в същите порядки.</text></scrape>