<scrape><title>The dinner</title><review_date>Sep 29, 2012</review_date><review_language>es</review_language><review_id>424700165</review_id><author>Lasiter</author><rating>liked it</rating><text>Este es uno de esos libros en lo que no me puede detener, lo leí de una sentada -aclaro que sentada para mi son varios días seguidos-, y por lo menos el 90% del tiempo me mantuvo concentrado en la trama y en la forma en que el autor entrelaza distintos momentos de la historia haciendo un cierre impecable.La historia es simple: una cena familiar en la que los protagonistas saben que tienen que tocar un tema crítico, relacionado con sus hijos y en la medida en que van sirviendo los platos vamos asistiendo a una crítica mordaz de este mundo moderno y su hipocresía hasta llegar a un desenlace inesperado. Interesantes reflexiones sobre el aborto, los limites de la solidaridad familiar y esa doble moral que tanto caracteriza estos tiempos. Muy recomendable. </text></scrape>