<scrape><title>The dinner</title><review_date>Apr 16, 2013</review_date><review_language></review_language><review_id>592066502</review_id><author>Colin</author><rating>it was amazing</rating><text>a brutal and twisted tale. it's one of those books you can read in the course of a day mainly because you can't put it down. as one review put it, by the time you're halfway through the book you've been taken to a place you never thought you would've consented to go in the first place. after this and cruddy, i need to read some mitch albom or something. sheesh.</text></scrape>